cmem_plugin_examples/__init__.py
cmem_plugin_examples/transform/__init__.py
cmem_plugin_examples/transform/lifetime.py
cmem_plugin_examples/workflow/__init__.py
cmem_plugin_examples/workflow/minimal.py
cmem_plugin_examples/workflow/random_values.py
cmem_plugin_examples/workflow/sleep.py
cmem_plugin_examples/workflow/user.py
cmem_plugin_examples-0.3.0.dist-info/LICENSE
cmem_plugin_examples-0.3.0.dist-info/METADATA
cmem_plugin_examples-0.3.0.dist-info/WHEEL
cmem_plugin_examples-0.3.0.dist-info/RECORD
