Metadata-Version: 2.1
Name: cmem-plugin-examples
Version: 0.3.0
Summary: Example plugins for eccenca Corporate Memory.
License: Apache-2.0
Keywords: eccenca Corporate Memory,plugins,DataIntegration
Author: eccenca
Author-email: cmempy-developer@eccenca.com
Maintainer: Sebastian Tramp
Maintainer-email: sebastian.tramp@eccenca.com
Requires-Python: >=3.11,<4.0
Classifier: Development Status :: 4 - Beta
Classifier: Environment :: Plugins
Classifier: License :: OSI Approved :: Apache Software License
Classifier: Programming Language :: Python :: 3
Classifier: Programming Language :: Python :: 3.11
Classifier: Topic :: Software Development :: Libraries :: Python Modules
Requires-Dist: cmem-plugin-base (>=4.0.0,<5.0.0)
